scriptsmith/__init__.py
scriptsmith/config.py
scriptsmith/main.py
scriptsmith/setup.py
scriptsmith/utils.py
scriptsmith-0.1.0.dist-info/licenses/LICENSE
scriptsmith-0.1.0.dist-info/METADATA
scriptsmith-0.1.0.dist-info/WHEEL
scriptsmith-0.1.0.dist-info/entry_points.txt
scriptsmith-0.1.0.dist-info/top_level.txt
scriptsmith-0.1.0.dist-info/RECORD
