Metadata-Version: 2.4
Name: scriptsmith
Version: 0.1.0
Summary: A CLI tool for managing tasks and scripts using Supabase
Author: Aditya Mathur
Author-email: aditya360@live.com
Classifier: Programming Language :: Python :: 3
Classifier: License :: OSI Approved :: MIT License
Classifier: Operating System :: OS Independent
Requires-Python: >=3.8
License-File: LICENSE
Requires-Dist: supabase
Requires-Dist: click
Requires-Dist: python-dotenv
Dynamic: author
Dynamic: author-email
Dynamic: classifier
Dynamic: license-file
Dynamic: requires-dist
Dynamic: requires-python
Dynamic: summary
